onhm/__init__.py
onhm/_version.py
onhm/bmi.py
onhm/cli.py
onhm/onhm.py
onhm-0.1.0.dist-info/LICENSE
onhm-0.1.0.dist-info/METADATA
onhm-0.1.0.dist-info/WHEEL
onhm-0.1.0.dist-info/entry_points.txt
onhm-0.1.0.dist-info/top_level.txt
onhm-0.1.0.dist-info/RECORD
